airflow_powerbi_plugin/__init__.py
airflow_powerbi_plugin/powerbi_plugin.py
airflow_powerbi_plugin/hooks/__init__.py
airflow_powerbi_plugin/hooks/powerbi.py
airflow_powerbi_plugin/operators/__init__.py
airflow_powerbi_plugin/operators/powerbi.py
airflow_powerbi_plugin-1.0.1.dist-info/LICENSE
airflow_powerbi_plugin-1.0.1.dist-info/METADATA
airflow_powerbi_plugin-1.0.1.dist-info/WHEEL
airflow_powerbi_plugin-1.0.1.dist-info/top_level.txt
airflow_powerbi_plugin-1.0.1.dist-info/RECORD
