Metadata-Version: 2.1
Name: airflow_powerbi_plugin
Version: 1.0.1
Summary: Airflow PowerBI plugin
Author-email: Ambika Garg <ambikagarg1101@gmail.com>
Project-URL: Homepage, https://github.com/ambika-garg/PowerBI_Airflow_Plugin
Classifier: Programming Language :: Python :: 3
Classifier: Development Status :: 3 - Alpha
Classifier: Environment :: Plugins
Classifier: Intended Audience :: Developers
Classifier: Topic :: Software Development :: Libraries :: Python Modules
Requires-Python: >=3.8
License-File: LICENSE
